eagle100/__init__.py
eagle100/eagle100.py
eagle100-0.1.1.dist-info/LICENSE
eagle100-0.1.1.dist-info/METADATA
eagle100-0.1.1.dist-info/WHEEL
eagle100-0.1.1.dist-info/top_level.txt
eagle100-0.1.1.dist-info/RECORD
