Metadata-Version: 2.1
Name: eagle100
Version: 0.1.1
Summary: Tool to read data from Rainforest Legacy Eagle.
Home-page: https://github.com/hastarin/eagle100
Author: Jon Benson
Author-email: jon.benson@hastarin.com
License: MIT
Keywords: rainforest eagle
Platform: UNKNOWN
Classifier: Development Status :: 4 - Beta
Classifier: Programming Language :: Python :: Implementation :: CPython
Classifier: Topic :: Home Automation
Requires-Python: >=3
License-File: LICENSE
